{"title":"플래텀 ─ Event","url":"https://platum.kr/event","favicon":"https://platum.kr/wp-content/uploads/2020/11/platum_logo-removebg-preview-100x100.png","elements":[{"title":"서울창업허브 공덕, 해외시장에서 통하는 혁신기업 찾아 투자 원스톱 지원","contents":"<div class=\"post_header_title\">\t\n\t\t\t\n\t\t\t\t   \t\t\t\t<!-- 원본 소스 BEGIN -->\n\t\t\t<!--\t\n\t\t\t\t<div class=\"post_info_cat\">\n\t\t\t\t\t<span>\n\t\t\t\t\t\t\t\t\t\t\t<a href=\"https://platum.kr/event\">Event</a>\n\t\t\t\t\t\t\t\t\t\t</span>\n\t\t\t\t</div>\n\t\t\t-->\n\t\t\t<!-- 원본 소스 END -->\n\n\t\t\t<!-- 카테고리 페이지 PC 접근 시 콘텐츠 카테고리 정보 노출 BEGIN -->\n\t\t\t\t\t\t\t\t<div class=\"post_info_cat\">\n\t\t\t\t\t\t<span>\n\t\t\t\t\t    \t\t\t\t\t        <a href=\"https://platum.kr/event\">Event</a>\n\t\t\t\t\t    \t\t\t\t\t\t</span>\n\t\t\t\t\t</div>\n\t\t\t\t\t\t<!-- 카테고리 페이지 PC 접근 시 콘텐츠 카테고리 정보 노출 END -->\n\t\t\t\t\t\t      \t<h5><a href=\"https://platum.kr/archives/206107\" title=\"서울창업허브 공덕, 해외시장에서 통하는 혁신기업 찾아 투자 원스톱 지원\">서울창업허브 공덕, 해외시장에서 통하는 혁신기업 찾아 투자 원스톱 지원</a></h5>\n\t\t\t      \t<div class=\"post_detail post_date\">\n\t\t\t      \t\t<span class=\"post_info_author\">\n\t\t\t\t\t\t\t\t\t\t\t\t\t\t<a href=\"https://platum.kr/archives/author/platum\"><span class=\"gravatar\"><img alt=\"Platum\" src=\"https://platum.kr/wp-content/uploads/2013/01/Platum_avatar.jpeg\" class=\"avatar avatar-60 photo\" width=\"60\" height=\"60\"></span><span style=\"float:left; margin:0 12px 0 -2px;\">Platum</span></a>\n\t\t\t\t\t\t\t\t\t\t      \t\t</span>\n\t\t\t      \t\t<span class=\"post_info_date\">\n\t\t\t      \t\t\t<a href=\"https://platum.kr/archives/206107\">Posted On 2023/04/27</a>\n\t\t\t      \t\t</span>\n\t\t\t\t  \t</div>\n\t\t\t   </div>\n\t\t\t   \n\t\t\t   <br class=\"clear\">\n\t    \t\n\t    \t\t\t\t\t\t\n\t\t\t\t    <div class=\"post_img\">\n\t\t\t\t        <a href=\"https://platum.kr/archives/206107\">\n\t\t\t\t        \t\t\t\t\t        \t<img src=\"https://platum.kr/wp-content/uploads/2023/04/hub-640x427.jpg\" alt=\"\" class=\"\" style=\"width:640px;height:427px;\">\n\t\t\t\t\t    </a>\n\t\t\t\t    </div>\n\t\t\t\t\n\t\t\t\t\t\t\t   \n\t\t\t   \t<br class=\"clear\">\n\t\t\t\t<!-- 원본 소스 BEGIN -->\n\t\t\t\t\t\t\t\t<!-- 원본 소스 END -->\n\n\t\t\t   <!-- Greater China 카테고리 페이지 중국어 글자 수 자르기 BEGIN -->\n\t\t\t   서울경제진흥원(SBA)이 기술기반 미래 혁신산업(테크 및 딥테크) 스타트업과 글로벌 진출 가능성이 있는 스타트업을 선발해 해외진출 가능성을 키울 수 있는 ‘역량강화 프로그램’을 진행한다. 서울창업허브 공덕에서는 처음으로 도입하는 프로그램이다. 우선, 총 15개 기업을 […]\t\t\t\t<!-- Greater China 카테고리 페이지 중국어 글자 수 자르기 END -->\n\t\t\t   <br class=\"clear\">\n\t\t\t    \n\t\t\t   <div class=\"post_button_wrapper\">\n\t\t\t   <a class=\"readmore\" href=\"https://platum.kr/archives/206107\">Continue Reading</a>\n\t\t\t   </div>\n\t\t\t    \n\t\t\t   <div class=\"post_info_comment\">\n\t\t\t\t<a href=\"https://platum.kr/archives/206107#respond\"><i class=\"fa fa-commenting\"></i>0</a>\n\t\t\t\t</div>\n\t\t\t\t\n\t\t\t\t\t\t\t    \t\t\t\t\n\t\t\t\t<br class=\"clear\"><hr class=\"post_divider\"><hr class=\"post_divider double\">","link":"https://platum.kr/archives/206107","retrieved":1682556954882,"image":"https://platum.kr/wp-content/uploads/2023/04/hub-640x427.jpg"},{"title":"2023 혁신의숲 어워즈 1차 후보 26개 기업 선정","contents":"<div class=\"post_header_title\">\t\n\t\t\t\n\t\t\t\t   \t\t\t\t<!-- 원본 소스 BEGIN -->\n\t\t\t<!--\t\n\t\t\t\t<div class=\"post_info_cat\">\n\t\t\t\t\t<span>\n\t\t\t\t\t\t\t\t\t\t\t<a href=\"https://platum.kr/event\">Event</a>\n\t\t\t\t\t\t\t\t\t\t\t&nbsp;/\n\t\t\t\t\t\t\t\t\t\t\t<a href=\"https://platum.kr/startup\">Startup</a>\n\t\t\t\t\t\t\t\t\t\t</span>\n\t\t\t\t</div>\n\t\t\t-->\n\t\t\t<!-- 원본 소스 END -->\n\n\t\t\t<!-- 카테고리 페이지 PC 접근 시 콘텐츠 카테고리 정보 노출 BEGIN -->\n\t\t\t\t\t\t\t\t<div class=\"post_info_cat\">\n\t\t\t\t\t\t<span>\n\t\t\t\t\t    \t\t\t\t\t        <a href=\"https://platum.kr/event\">Event</a>\n\t\t\t\t\t    \t\t\t\t\t        &nbsp;/\n\t\t\t\t\t    \t\t\t\t\t        <a href=\"https://platum.kr/startup\">Startup</a>\n\t\t\t\t\t    \t\t\t\t\t\t</span>\n\t\t\t\t\t</div>\n\t\t\t\t\t\t<!-- 카테고리 페이지 PC 접근 시 콘텐츠 카테고리 정보 노출 END -->\n\t\t\t\t\t\t      \t<h5><a href=\"https://platum.kr/archives/206074\" title=\"2023 혁신의숲 어워즈 1차 후보 26개 기업 선정\">2023 혁신의숲 어워즈 1차 후보 26개 기업 선정</a></h5>\n\t\t\t      \t<div class=\"post_detail post_date\">\n\t\t\t      \t\t<span class=\"post_info_author\">\n\t\t\t\t\t\t\t\t\t\t\t\t\t\t<a href=\"https://platum.kr/archives/author/platum\"><span class=\"gravatar\"><img alt=\"Platum\" src=\"https://platum.kr/wp-content/uploads/2013/01/Platum_avatar.jpeg\" class=\"avatar avatar-60 photo\" width=\"60\" height=\"60\"></span><span style=\"float:left; margin:0 12px 0 -2px;\">Platum</span></a>\n\t\t\t\t\t\t\t\t\t\t      \t\t</span>\n\t\t\t      \t\t<span class=\"post_info_date\">\n\t\t\t      \t\t\t<a href=\"https://platum.kr/archives/206074\">Posted On 2023/04/27</a>\n\t\t\t      \t\t</span>\n\t\t\t\t  \t</div>\n\t\t\t   </div>\n\t\t\t   \n\t\t\t   <br class=\"clear\">\n\t    \t\n\t    \t\t\t\t\t\t\n\t\t\t\t    <div class=\"post_img\">\n\t\t\t\t        <a href=\"https://platum.kr/archives/206074\">\n\t\t\t\t        \t\t\t\t\t        \t<img src=\"https://platum.kr/wp-content/uploads/2023/04/inno-640x427.jpg\" alt=\"\" class=\"\" style=\"width:640px;height:427px;\">\n\t\t\t\t\t    </a>\n\t\t\t\t    </div>\n\t\t\t\t\n\t\t\t\t\t\t\t   \n\t\t\t   \t<br class=\"clear\">\n\t\t\t\t<!-- 원본 소스 BEGIN -->\n\t\t\t\t\t\t\t\t<!-- 원본 소스 END -->\n\n\t\t\t   <!-- Greater China 카테고리 페이지 중국어 글자 수 자르기 BEGIN -->\n\t\t\t   ‘혁신의숲’ 어워즈 운영사인 마크앤컴퍼니가 2023년 혁신의숲 어워즈 1차 후보 스타트업 26개사를 공개했다. 혁신의숲 어워즈는 스타트업 성장의 핵심지표라 볼 수 있는 활성 사용자 수, 소비자 거래액, 고용 등 비즈니스 성장을 입증할 수 있는 실제[…]\t\t\t\t<!-- Greater China 카테고리 페이지 중국어 글자 수 자르기 END -->\n\t\t\t   <br class=\"clear\">\n\t\t\t    \n\t\t\t   <div class=\"post_button_wrapper\">\n\t\t\t   <a class=\"readmore\" href=\"https://platum.kr/archives/206074\">Continue Reading</a>\n\t\t\t   </div>\n\t\t\t    \n\t\t\t   <div class=\"post_info_comment\">\n\t\t\t\t<a href=\"https://platum.kr/archives/206074#respond\"><i class=\"fa fa-commenting\"></i>0</a>\n\t\t\t\t</div>\n\t\t\t\t\n\t\t\t\t\t\t\t    \t\t\t\t\n\t\t\t\t<br class=\"clear\"><hr class=\"post_divider\"><hr class=\"post_divider double\">","link":"https://platum.kr/archives/206074","retrieved":1682556954888,"image":"https://platum.kr/wp-content/uploads/2023/04/inno-640x427.jpg"},{"title":"아산나눔재단, 포용적 창업지원 프로그램 ‘아산상회’ 입학식 진행","contents":"<div class=\"post_header_title\">\t\n\t\t\t\n\t\t\t\t   \t\t\t\t<!-- 원본 소스 BEGIN -->\n\t\t\t<!--\t\n\t\t\t\t<div class=\"post_info_cat\">\n\t\t\t\t\t<span>\n\t\t\t\t\t\t\t\t\t\t\t<a href=\"https://platum.kr/event\">Event</a>\n\t\t\t\t\t\t\t\t\t\t\t&nbsp;/\n\t\t\t\t\t\t\t\t\t\t\t<a href=\"https://platum.kr/startup\">Startup</a>\n\t\t\t\t\t\t\t\t\t\t</span>\n\t\t\t\t</div>\n\t\t\t-->\n\t\t\t<!-- 원본 소스 END -->\n\n\t\t\t<!-- 카테고리 페이지 PC 접근 시 콘텐츠 카테고리 정보 노출 BEGIN -->\n\t\t\t\t\t\t\t\t<div class=\"post_info_cat\">\n\t\t\t\t\t\t<span>\n\t\t\t\t\t    \t\t\t\t\t        <a href=\"https://platum.kr/event\">Event</a>\n\t\t\t\t\t    \t\t\t\t\t        &nbsp;/\n\t\t\t\t\t    \t\t\t\t\t        <a href=\"https://platum.kr/startup\">Startup</a>\n\t\t\t\t\t    \t\t\t\t\t\t</span>\n\t\t\t\t\t</div>\n\t\t\t\t\t\t<!-- 카테고리 페이지 PC 접근 시 콘텐츠 카테고리 정보 노출 END -->\n\t\t\t\t\t\t      \t<h5><a href=\"https://platum.kr/archives/206067\" title=\"아산나눔재단, 포용적 창업지원 프로그램 ‘아산상회’ 입학식 진행\">아산나눔재단, 포용적 창업지원 프로그램 ‘아산상회’ 입학식 진행</a></h5>\n\t\t\t      \t<div class=\"post_detail post_date\">\n\t\t\t      \t\t<span class=\"post_info_author\">\n\t\t\t\t\t\t\t\t\t\t\t\t\t\t<a href=\"https://platum.kr/archives/author/mj-kim\"><span class=\"gravatar\"><img alt=\"김민정\" src=\"https://platum.kr/wp-content/uploads/2019/05/김민정_avatar_1557275307-60x60.jpg\" class=\"avatar avatar-60 photo\" width=\"60\" height=\"60\"></span><span style=\"float:left; margin:0 12px 0 -2px;\">김민정</span></a>\n\t\t\t\t\t\t\t\t\t\t      \t\t</span>\n\t\t\t      \t\t<span class=\"post_info_date\">\n\t\t\t      \t\t\t<a href=\"https://platum.kr/archives/206067\">Posted On 2023/04/27</a>\n\t\t\t      \t\t</span>\n\t\t\t\t  \t</div>\n\t\t\t   </div>\n\t\t\t   \n\t\t\t   <br class=\"clear\">\n\t    \t\n\t    \t\t\t\t\t\t\n\t\t\t\t    <div class=\"post_img\">\n\t\t\t\t        <a href=\"https://platum.kr/archives/206067\">\n\t\t\t\t        \t\t\t\t\t        \t<img src=\"https://platum.kr/wp-content/uploads/2023/04/asan-1-640x427.jpg\" alt=\"\" class=\"\" style=\"width:640px;height:427px;\">\n\t\t\t\t\t    </a>\n\t\t\t\t    </div>\n\t\t\t\t\n\t\t\t\t\t\t\t   \n\t\t\t   \t<br class=\"clear\">\n\t\t\t\t<!-- 원본 소스 BEGIN -->\n\t\t\t\t\t\t\t\t<!-- 원본 소스 END -->\n\n\t\t\t   <!-- Greater China 카테고리 페이지 중국어 글자 수 자르기 BEGIN -->\n\t\t\t   아산나눔재단이 26일 서울 강남구 역삼동 마루180에서 ‘아산상회’ 입학식을 개최했다. 아산상회는 아산 정주영 회장의 호인 ‘아산(峨山)’과 그가 생전 처음으로 창업한 ‘경일상회’의 합성어로 북한이탈 청년 창업가가 기업가정신을 함양하고 창업을 통해 자립 및 성장하는 것[…]\t\t\t\t<!-- Greater China 카테고리 페이지 중국어 글자 수 자르기 END -->\n\t\t\t   <br class=\"clear\">\n\t\t\t    \n\t\t\t   <div class=\"post_button_wrapper\">\n\t\t\t   <a class=\"readmore\" href=\"https://platum.kr/archives/206067\">Continue Reading</a>\n\t\t\t   </div>\n\t\t\t    \n\t\t\t   <div class=\"post_info_comment\">\n\t\t\t\t<a href=\"https://platum.kr/archives/206067#respond\"><i class=\"fa fa-commenting\"></i>0</a>\n\t\t\t\t</div>\n\t\t\t\t\n\t\t\t\t\t\t\t    \t\t\t\t\n\t\t\t\t<br class=\"clear\"><hr class=\"post_divider\"><hr class=\"post_divider double\">","link":"https://platum.kr/archives/206067","retrieved":1682556954890,"image":"https://platum.kr/wp-content/uploads/2023/04/asan-1-640x427.jpg"},{"title":"한국엔젤투자협회, 2023년 팁스 사업설명회 개최","contents":"<div class=\"post_header_title\">\t\n\t\t\t\n\t\t\t\t   \t\t\t\t<!-- 원본 소스 BEGIN -->\n\t\t\t<!--\t\n\t\t\t\t<div class=\"post_info_cat\">\n\t\t\t\t\t<span>\n\t\t\t\t\t\t\t\t\t\t\t<a href=\"https://platum.kr/event\">Event</a>\n\t\t\t\t\t\t\t\t\t\t</span>\n\t\t\t\t</div>\n\t\t\t-->\n\t\t\t<!-- 원본 소스 END -->\n\n\t\t\t<!-- 카테고리 페이지 PC 접근 시 콘텐츠 카테고리 정보 노출 BEGIN -->\n\t\t\t\t\t\t\t\t<div class=\"post_info_cat\">\n\t\t\t\t\t\t<span>\n\t\t\t\t\t    \t\t\t\t\t        <a href=\"https://platum.kr/event\">Event</a>\n\t\t\t\t\t    \t\t\t\t\t\t</span>\n\t\t\t\t\t</div>\n\t\t\t\t\t\t<!-- 카테고리 페이지 PC 접근 시 콘텐츠 카테고리 정보 노출 END -->\n\t\t\t\t\t\t      \t<h5><a href=\"https://platum.kr/archives/206059\" title=\"한국엔젤투자협회, 2023년 팁스 사업설명회 개최\">한국엔젤투자협회, 2023년 팁스 사업설명회 개최</a></h5>\n\t\t\t      \t<div class=\"post_detail post_date\">\n\t\t\t      \t\t<span class=\"post_info_author\">\n\t\t\t\t\t\t\t\t\t\t\t\t\t\t<a href=\"https://platum.kr/archives/author/platum\"><span class=\"gravatar\"><img alt=\"Platum\" src=\"https://platum.kr/wp-content/uploads/2013/01/Platum_avatar.jpeg\" class=\"avatar avatar-60 photo\" width=\"60\" height=\"60\"></span><span style=\"float:left; margin:0 12px 0 -2px;\">Platum</span></a>\n\t\t\t\t\t\t\t\t\t\t      \t\t</span>\n\t\t\t      \t\t<span class=\"post_info_date\">\n\t\t\t      \t\t\t<a href=\"https://platum.kr/archives/206059\">Posted On 2023/04/26</a>\n\t\t\t      \t\t</span>\n\t\t\t\t  \t</div>\n\t\t\t   </div>\n\t\t\t   \n\t\t\t   <br class=\"clear\">\n\t    \t\n\t    \t\t\t\t\t\t\n\t\t\t\t    <div class=\"post_img\">\n\t\t\t\t        <a href=\"https://platum.kr/archives/206059\">\n\t\t\t\t        \t\t\t\t\t        \t<img src=\"https://platum.kr/wp-content/uploads/2023/04/tips-640x427.jpg\" alt=\"\" class=\"\" style=\"width:640px;height:427px;\">\n\t\t\t\t\t    </a>\n\t\t\t\t    </div>\n\t\t\t\t\n\t\t\t\t\t\t\t   \n\t\t\t   \t<br class=\"clear\">\n\t\t\t\t<!-- 원본 소스 BEGIN -->\n\t\t\t\t\t\t\t\t<!-- 원본 소스 END -->\n\n\t\t\t   <!-- Greater China 카테고리 페이지 중국어 글자 수 자르기 BEGIN -->\n\t\t\t   한국엔젤투자협회가 민간투자와 연계하여 초기 유망 창업기업을 발굴‧지원하기 위한 ‘2023년 팁스(TIPS) 사업설명회’를 개최한다. 이번 사업설명회는 ‘23. 5. 16(화) 서울(팁스타운)을 시작으로, 4개 권역(대전,대구,부산,광주) 총 5개 […]\t\t\t\t<!-- Greater China 카테고리 페이지 중국어 글자 수 자르기 END -->\n\t\t\t   <br class=\"clear\">\n\t\t\t    \n\t\t\t   <div class=\"post_button_wrapper\">\n\t\t\t   <a class=\"readmore\" href=\"https://platum.kr/archives/206059\">Continue Reading</a>\n\t\t\t   </div>\n\t\t\t    \n\t\t\t   <div class=\"post_info_comment\">\n\t\t\t\t<a href=\"https://platum.kr/archives/206059#respond\"><i class=\"fa fa-commenting\"></i>0</a>\n\t\t\t\t</div>\n\t\t\t\t\n\t\t\t\t\t\t\t    \t\t\t\t\n\t\t\t\t<br class=\"clear\"><hr class=\"post_divider\"><hr class=\"post_divider double\">","link":"https://platum.kr/archives/206059","retrieved":1682543567145,"image":"https://platum.kr/wp-content/uploads/2023/04/tips-640x427.jpg"},{"title":"[스타트업 단신] 우아한형제들, 원티드랩, 디라이트, 파이퍼","contents":"<div class=\"post_header_title\">\t\n\t\t\t\n\t\t\t\t   \t\t\t\t<!-- 원본 소스 BEGIN -->\n\t\t\t<!--\t\n\t\t\t\t<div class=\"post_info_cat\">\n\t\t\t\t\t<span>\n\t\t\t\t\t\t\t\t\t\t\t<a href=\"https://platum.kr/event\">Event</a>\n\t\t\t\t\t\t\t\t\t\t\t&nbsp;/\n\t\t\t\t\t\t\t\t\t\t\t<a href=\"https://platum.kr/startup\">Startup</a>\n\t\t\t\t\t\t\t\t\t\t</span>\n\t\t\t\t</div>\n\t\t\t-->\n\t\t\t<!-- 원본 소스 END -->\n\n\t\t\t<!-- 카테고리 페이지 PC 접근 시 콘텐츠 카테고리 정보 노출 BEGIN -->\n\t\t\t\t\t\t\t\t<div class=\"post_info_cat\">\n\t\t\t\t\t\t<span>\n\t\t\t\t\t    \t\t\t\t\t        <a href=\"https://platum.kr/event\">Event</a>\n\t\t\t\t\t    \t\t\t\t\t        &nbsp;/\n\t\t\t\t\t    \t\t\t\t\t        <a href=\"https://platum.kr/startup\">Startup</a>\n\t\t\t\t\t    \t\t\t\t\t\t</span>\n\t\t\t\t\t</div>\n\t\t\t\t\t\t<!-- 카테고리 페이지 PC 접근 시 콘텐츠 카테고리 정보 노출 END -->\n\t\t\t\t\t\t      \t<h5><a href=\"https://platum.kr/archives/206021\" title=\"[스타트업 단신] 우아한형제들, 원티드랩, 디라이트, 파이퍼\">[스타트업 단신] 우아한형제들, 원티드랩, 디라이트, 파이퍼</a></h5>\n\t\t\t      \t<div class=\"post_detail post_date\">\n\t\t\t      \t\t<span class=\"post_info_author\">\n\t\t\t\t\t\t\t\t\t\t\t\t\t\t<a href=\"https://platum.kr/archives/author/platum\"><span class=\"gravatar\"><img alt=\"Platum\" src=\"https://platum.kr/wp-content/uploads/2013/01/Platum_avatar.jpeg\" class=\"avatar avatar-60 photo\" width=\"60\" height=\"60\"></span><span style=\"float:left; margin:0 12px 0 -2px;\">Platum</span></a>\n\t\t\t\t\t\t\t\t\t\t      \t\t</span>\n\t\t\t      \t\t<span class=\"post_info_date\">\n\t\t\t      \t\t\t<a href=\"https://platum.kr/archives/206021\">Posted On 2023/04/26</a>\n\t\t\t      \t\t</span>\n\t\t\t\t  \t</div>\n\t\t\t   </div>\n\t\t\t   \n\t\t\t   <br class=\"clear\">\n\t    \t\n\t    \t\t\t\t\t\t\n\t\t\t\t    <div class=\"post_img\">\n\t\t\t\t        <a href=\"https://platum.kr/archives/206021\">\n\t\t\t\t        \t\t\t\t\t        \t<img src=\"https://platum.kr/wp-content/uploads/2023/04/bb-6-640x427.jpg\" alt=\"\" class=\"\" style=\"width:640px;height:427px;\">\n\t\t\t\t\t    </a>\n\t\t\t\t    </div>\n\t\t\t\t\n\t\t\t\t\t\t\t   \n\t\t\t   \t<br class=\"clear\">\n\t\t\t\t<!-- 원본 소스 BEGIN -->\n\t\t\t\t\t\t\t\t<!-- 원본 소스 END -->\n\n\t\t\t   <!-- Greater China 카테고리 페이지 중국어 글자 수 자르기 BEGIN -->\n\t\t\t   배민, 외식업 실전 세미나 ‘포커스데이’ 개최 배달앱 배달의민족을 운영하는 우아한형제들이 배민아카데미를 통해 지난 24일부터 ‘배민 포커스데이’를 시작했다. ‘배민 포커스데이’는 배민아카데미가 외식업 자영업자나 예비 창업자를 위해 만든 집중 세미나 프로그램이다. 4가지[…]\t\t\t\t<!-- Greater China 카테고리 페이지 중국어 글자 수 자르기 END -->\n\t\t\t   <br class=\"clear\">\n\t\t\t    \n\t\t\t   <div class=\"post_button_wrapper\">\n\t\t\t   <a class=\"readmore\" href=\"https://platum.kr/archives/206021\">Continue Reading</a>\n\t\t\t   </div>\n\t\t\t    \n\t\t\t   <div class=\"post_info_comment\">\n\t\t\t\t<a href=\"https://platum.kr/archives/206021#respond\"><i class=\"fa fa-commenting\"></i>0</a>\n\t\t\t\t</div>\n\t\t\t\t\n\t\t\t\t\t\t\t    \t\t\t\t\n\t\t\t\t<br class=\"clear\"><hr class=\"post_divider\"><hr class=\"post_divider double\">","link":"https://platum.kr/archives/206021","retrieved":1682543567147,"image":"https://platum.kr/wp-content/uploads/2023/04/bb-6-640x427.jpg"},{"title":"우리금융그룹 스타트업 협력 프로그램 ‘디노랩’ 4기 모집","contents":"<div class=\"post_header_title\">\t\n\t\t\t\n\t\t\t\t   \t\t\t\t<!-- 원본 소스 BEGIN -->\n\t\t\t<!--\t\n\t\t\t\t<div class=\"post_info_cat\">\n\t\t\t\t\t<span>\n\t\t\t\t\t\t\t\t\t\t\t<a href=\"https://platum.kr/event\">Event</a>\n\t\t\t\t\t\t\t\t\t\t</span>\n\t\t\t\t</div>\n\t\t\t-->\n\t\t\t<!-- 원본 소스 END -->\n\n\t\t\t<!-- 카테고리 페이지 PC 접근 시 콘텐츠 카테고리 정보 노출 BEGIN -->\n\t\t\t\t\t\t\t\t<div class=\"post_info_cat\">\n\t\t\t\t\t\t<span>\n\t\t\t\t\t    \t\t\t\t\t        <a href=\"https://platum.kr/event\">Event</a>\n\t\t\t\t\t    \t\t\t\t\t\t</span>\n\t\t\t\t\t</div>\n\t\t\t\t\t\t<!-- 카테고리 페이지 PC 접근 시 콘텐츠 카테고리 정보 노출 END -->\n\t\t\t\t\t\t      \t<h5><a href=\"https://platum.kr/archives/206042\" title=\"우리금융그룹 스타트업 협력 프로그램 ‘디노랩’ 4기 모집\">우리금융그룹 스타트업 협력 프로그램 ‘디노랩’ 4기 모집</a></h5>\n\t\t\t      \t<div class=\"post_detail post_date\">\n\t\t\t      \t\t<span class=\"post_info_author\">\n\t\t\t\t\t\t\t\t\t\t\t\t\t\t<a href=\"https://platum.kr/archives/author/platum\"><span class=\"gravatar\"><img alt=\"Platum\" src=\"https://platum.kr/wp-content/uploads/2013/01/Platum_avatar.jpeg\" class=\"avatar avatar-60 photo\" width=\"60\" height=\"60\"></span><span style=\"float:left; margin:0 12px 0 -2px;\">Platum</span></a>\n\t\t\t\t\t\t\t\t\t\t      \t\t</span>\n\t\t\t      \t\t<span class=\"post_info_date\">\n\t\t\t      \t\t\t<a href=\"https://platum.kr/archives/206042\">Posted On 2023/04/26</a>\n\t\t\t      \t\t</span>\n\t\t\t\t  \t</div>\n\t\t\t   </div>\n\t\t\t   \n\t\t\t   <br class=\"clear\">\n\t    \t\n\t    \t\t\t\t\t\t\n\t\t\t\t    <div class=\"post_img\">\n\t\t\t\t        <a href=\"https://platum.kr/archives/206042\">\n\t\t\t\t        \t\t\t\t\t        \t<img src=\"https://platum.kr/wp-content/uploads/2023/04/dd-2-640x427.jpg\" alt=\"\" class=\"\" style=\"width:640px;height:427px;\">\n\t\t\t\t\t    </a>\n\t\t\t\t    </div>\n\t\t\t\t\n\t\t\t\t\t\t\t   \n\t\t\t   \t<br class=\"clear\">\n\t\t\t\t<!-- 원본 소스 BEGIN -->\n\t\t\t\t\t\t\t\t<!-- 원본 소스 END -->\n\n\t\t\t   <!-- Greater China 카테고리 페이지 중국어 글자 수 자르기 BEGIN -->\n\t\t\t   우리금융그룹이 스타트업 협력 프로그램인 ‘디노랩'(Digital Innovation Lab) 4기에 참여할 기업을 모집한다. 우리금융은 디노랩을 통해 그간 116개 기업에 사업협력 33건과 1174억 규모의 직·간접투자 기회를 제공했다. 이번 모집을 통해 우[…]\t\t\t\t<!-- Greater China 카테고리 페이지 중국어 글자 수 자르기 END -->\n\t\t\t   <br class=\"clear\">\n\t\t\t    \n\t\t\t   <div class=\"post_button_wrapper\">\n\t\t\t   <a class=\"readmore\" href=\"https://platum.kr/archives/206042\">Continue Reading</a>\n\t\t\t   </div>\n\t\t\t    \n\t\t\t   <div class=\"post_info_comment\">\n\t\t\t\t<a href=\"https://platum.kr/archives/206042#respond\"><i class=\"fa fa-commenting\"></i>0</a>\n\t\t\t\t</div>\n\t\t\t\t\n\t\t\t\t\t\t\t    \t\t\t\t\n\t\t\t\t<br class=\"clear\"><hr class=\"post_divider\"><hr class=\"post_divider double\">","link":"https://platum.kr/archives/206042","retrieved":1682543567148,"image":"https://platum.kr/wp-content/uploads/2023/04/dd-2-640x427.jpg"},{"title":"젠엑시스, ‘2023년 민간협력 여성벤처 · 스타트업 육성’ 참여기업 모집","contents":"<div class=\"post_header_title\">\t\n\t\t\t\n\t\t\t\t   \t\t\t\t<!-- 원본 소스 BEGIN -->\n\t\t\t<!--\t\n\t\t\t\t<div class=\"post_info_cat\">\n\t\t\t\t\t<span>\n\t\t\t\t\t\t\t\t\t\t\t<a href=\"https://platum.kr/event\">Event</a>\n\t\t\t\t\t\t\t\t\t\t</span>\n\t\t\t\t</div>\n\t\t\t-->\n\t\t\t<!-- 원본 소스 END -->\n\n\t\t\t<!-- 카테고리 페이지 PC 접근 시 콘텐츠 카테고리 정보 노출 BEGIN -->\n\t\t\t\t\t\t\t\t<div class=\"post_info_cat\">\n\t\t\t\t\t\t<span>\n\t\t\t\t\t    \t\t\t\t\t        <a href=\"https://platum.kr/event\">Event</a>\n\t\t\t\t\t    \t\t\t\t\t\t</span>\n\t\t\t\t\t</div>\n\t\t\t\t\t\t<!-- 카테고리 페이지 PC 접근 시 콘텐츠 카테고리 정보 노출 END -->\n\t\t\t\t\t\t      \t<h5><a href=\"https://platum.kr/archives/206030\" title=\"젠엑시스, ‘2023년 민간협력 여성벤처 · 스타트업 육성’ 참여기업 모집\">젠엑시스, ‘2023년 민간협력 여성벤처 · 스타트업 육성’ 참여기업 모집</a></h5>\n\t\t\t      \t<div class=\"post_detail post_date\">\n\t\t\t      \t\t<span class=\"post_info_author\">\n\t\t\t\t\t\t\t\t\t\t\t\t\t\t<a href=\"https://platum.kr/archives/author/platum\"><span class=\"gravatar\"><img alt=\"Platum\" src=\"https://platum.kr/wp-content/uploads/2013/01/Platum_avatar.jpeg\" class=\"avatar avatar-60 photo\" width=\"60\" height=\"60\"></span><span style=\"float:left; margin:0 12px 0 -2px;\">Platum</span></a>\n\t\t\t\t\t\t\t\t\t\t      \t\t</span>\n\t\t\t      \t\t<span class=\"post_info_date\">\n\t\t\t      \t\t\t<a href=\"https://platum.kr/archives/206030\">Posted On 2023/04/26</a>\n\t\t\t      \t\t</span>\n\t\t\t\t  \t</div>\n\t\t\t   </div>\n\t\t\t   \n\t\t\t   <br class=\"clear\">\n\t    \t\n\t    \t\t\t\t\t\t\n\t\t\t\t    <div class=\"post_img\">\n\t\t\t\t        <a href=\"https://platum.kr/archives/206030\">\n\t\t\t\t        \t\t\t\t\t        \t<img src=\"https://platum.kr/wp-content/uploads/2023/04/unnamed-1-7-640x427.png\" alt=\"\" class=\"\" style=\"width:640px;height:427px;\">\n\t\t\t\t\t    </a>\n\t\t\t\t    </div>\n\t\t\t\t\n\t\t\t\t\t\t\t   \n\t\t\t   \t<br class=\"clear\">\n\t\t\t\t<!-- 원본 소스 BEGIN -->\n\t\t\t\t\t\t\t\t<!-- 원본 소스 END -->\n\n\t\t\t   <!-- Greater China 카테고리 페이지 중국어 글자 수 자르기 BEGIN -->\n\t\t\t   바이오·헬스케어 특화 액셀러레이터(AC) 젠엑시스가 운영하고 한국여성벤처협회가 주관하는 2023년 민간협력 여성특화 액셀러레이팅 프로그램 ‘Women Founders Planet’이 시작된다. 지원대상은 기술기반 혁신아이템, 여성 특화 및 친화제품 등을 보유한 여성 예[…]\t\t\t\t<!-- Greater China 카테고리 페이지 중국어 글자 수 자르기 END -->\n\t\t\t   <br class=\"clear\">\n\t\t\t    \n\t\t\t   <div class=\"post_button_wrapper\">\n\t\t\t   <a class=\"readmore\" href=\"https://platum.kr/archives/206030\">Continue Reading</a>\n\t\t\t   </div>\n\t\t\t    \n\t\t\t   <div class=\"post_info_comment\">\n\t\t\t\t<a href=\"https://platum.kr/archives/206030#respond\"><i class=\"fa fa-commenting\"></i>0</a>\n\t\t\t\t</div>\n\t\t\t\t\n\t\t\t\t\t\t\t    \t\t\t\t\n\t\t\t\t<br class=\"clear\"><hr class=\"post_divider\"><hr class=\"post_divider double\">","link":"https://platum.kr/archives/206030","retrieved":1682543567150,"image":"https://platum.kr/wp-content/uploads/2023/04/unnamed-1-7-640x427.png"},{"title":"네이버웹툰 PPS 프로그램 10주년, 연간 규모 2조 255억 원","contents":"<div class=\"post_header_title\">\t\n\t\t\t\n\t\t\t\t   \t\t\t\t<!-- 원본 소스 BEGIN -->\n\t\t\t<!--\t\n\t\t\t\t<div class=\"post_info_cat\">\n\t\t\t\t\t<span>\n\t\t\t\t\t\t\t\t\t\t\t<a href=\"https://platum.kr/business\">Business</a>\n\t\t\t\t\t\t\t\t\t\t\t&nbsp;/\n\t\t\t\t\t\t\t\t\t\t\t<a href=\"https://platum.kr/event\">Event</a>\n\t\t\t\t\t\t\t\t\t\t</span>\n\t\t\t\t</div>\n\t\t\t-->\n\t\t\t<!-- 원본 소스 END -->\n\n\t\t\t<!-- 카테고리 페이지 PC 접근 시 콘텐츠 카테고리 정보 노출 BEGIN -->\n\t\t\t\t\t\t\t\t<div class=\"post_info_cat\">\n\t\t\t\t\t\t<span>\n\t\t\t\t\t    \t\t\t\t\t        <a href=\"https://platum.kr/business\">Business</a>\n\t\t\t\t\t    \t\t\t\t\t        &nbsp;/\n\t\t\t\t\t    \t\t\t\t\t        <a href=\"https://platum.kr/event\">Event</a>\n\t\t\t\t\t    \t\t\t\t\t\t</span>\n\t\t\t\t\t</div>\n\t\t\t\t\t\t<!-- 카테고리 페이지 PC 접근 시 콘텐츠 카테고리 정보 노출 END -->\n\t\t\t\t\t\t      \t<h5><a href=\"https://platum.kr/archives/205924\" title=\"네이버웹툰 PPS 프로그램 10주년, 연간 규모 2조 255억 원\">네이버웹툰 PPS 프로그램 10주년, 연간 규모 2조 255억 원</a></h5>\n\t\t\t      \t<div class=\"post_detail post_date\">\n\t\t\t      \t\t<span class=\"post_info_author\">\n\t\t\t\t\t\t\t\t\t\t\t\t\t\t<a href=\"https://platum.kr/archives/author/choi\"><span class=\"gravatar\"><img alt=\"최원희\" src=\"https://platum.kr/wp-content/uploads/2021/07/최원희_avatar_1625374313-60x60.jpg\" class=\"avatar avatar-60 photo\" width=\"60\" height=\"60\"></span><span style=\"float:left; margin:0 12px 0 -2px;\">최원희</span></a>\n\t\t\t\t\t\t\t\t\t\t      \t\t</span>\n\t\t\t      \t\t<span class=\"post_info_date\">\n\t\t\t      \t\t\t<a href=\"https://platum.kr/archives/205924\">Posted On 2023/04/25</a>\n\t\t\t      \t\t</span>\n\t\t\t\t  \t</div>\n\t\t\t   </div>\n\t\t\t   \n\t\t\t   <br class=\"clear\">\n\t    \t\n\t    \t\t\t\t\t\t\n\t\t\t\t    <div class=\"post_img\">\n\t\t\t\t        <a href=\"https://platum.kr/archives/205924\">\n\t\t\t\t        \t\t\t\t\t        \t<img src=\"https://platum.kr/wp-content/uploads/2023/04/PPS-640x427.jpg\" alt=\"\" class=\"\" style=\"width:640px;height:427px;\">\n\t\t\t\t\t    </a>\n\t\t\t\t    </div>\n\t\t\t\t\n\t\t\t\t\t\t\t   \n\t\t\t   \t<br class=\"clear\">\n\t\t\t\t<!-- 원본 소스 BEGIN -->\n\t\t\t\t\t\t\t\t<!-- 원본 소스 END -->\n\n\t\t\t   <!-- Greater China 카테고리 페이지 중국어 글자 수 자르기 BEGIN -->\n\t\t\t   네이버웹툰이 창작자 수익 다각화를 위해 마련한 웹툰 비즈니스 모델 패키지&nbsp;‘PPS&nbsp;프로그램’이 출시&nbsp;10주년을 맞았다. 10년 사이&nbsp;PPS&nbsp;프로그램의 연간 규모는&nbsp;2조 원 넘게 증가했다. 네이버웹툰은&nbsp;25일&nbsp;PPS&nbsp;프로그램&nbsp;10주년을 맞아 그간의 성과를 공개하는 미디어[…]\t\t\t\t<!-- Greater China 카테고리 페이지 중국어 글자 수 자르기 END -->\n\t\t\t   <br class=\"clear\">\n\t\t\t    \n\t\t\t   <div class=\"post_button_wrapper\">\n\t\t\t   <a class=\"readmore\" href=\"https://platum.kr/archives/205924\">Continue Reading</a>\n\t\t\t   </div>\n\t\t\t    \n\t\t\t   <div class=\"post_info_comment\">\n\t\t\t\t<a href=\"https://platum.kr/archives/205924#respond\"><i class=\"fa fa-commenting\"></i>0</a>\n\t\t\t\t</div>\n\t\t\t\t\n\t\t\t\t\t\t\t    \t\t\t\t\n\t\t\t\t<br class=\"clear\"><hr class=\"post_divider\"><hr class=\"post_divider double\">","link":"https://platum.kr/archives/205924","retrieved":1682543567151,"image":"https://platum.kr/wp-content/uploads/2023/04/PPS-640x427.jpg"},{"title":"뉴욕 맨해튼에 개방형 공유공간 ‘글로벌비즈니스센터(GBC)’ 개소","contents":"<div class=\"post_header_title\">\t\n\t\t\t\n\t\t\t\t   \t\t\t\t<!-- 원본 소스 BEGIN -->\n\t\t\t<!--\t\n\t\t\t\t<div class=\"post_info_cat\">\n\t\t\t\t\t<span>\n\t\t\t\t\t\t\t\t\t\t\t<a href=\"https://platum.kr/event\">Event</a>\n\t\t\t\t\t\t\t\t\t\t\t&nbsp;/\n\t\t\t\t\t\t\t\t\t\t\t<a href=\"https://platum.kr/trends\">Trends</a>\n\t\t\t\t\t\t\t\t\t\t</span>\n\t\t\t\t</div>\n\t\t\t-->\n\t\t\t<!-- 원본 소스 END -->\n\n\t\t\t<!-- 카테고리 페이지 PC 접근 시 콘텐츠 카테고리 정보 노출 BEGIN -->\n\t\t\t\t\t\t\t\t<div class=\"post_info_cat\">\n\t\t\t\t\t\t<span>\n\t\t\t\t\t    \t\t\t\t\t        <a href=\"https://platum.kr/event\">Event</a>\n\t\t\t\t\t    \t\t\t\t\t        &nbsp;/\n\t\t\t\t\t    \t\t\t\t\t        <a href=\"https://platum.kr/trends\">Trends</a>\n\t\t\t\t\t    \t\t\t\t\t\t</span>\n\t\t\t\t\t</div>\n\t\t\t\t\t\t<!-- 카테고리 페이지 PC 접근 시 콘텐츠 카테고리 정보 노출 END -->\n\t\t\t\t\t\t      \t<h5><a href=\"https://platum.kr/archives/205957\" title=\"뉴욕 맨해튼에 개방형 공유공간 ‘글로벌비즈니스센터(GBC)’ 개소\">뉴욕 맨해튼에 개방형 공유공간 ‘글로벌비즈니스센터(GBC)’ 개소</a></h5>\n\t\t\t      \t<div class=\"post_detail post_date\">\n\t\t\t      \t\t<span class=\"post_info_author\">\n\t\t\t\t\t\t\t\t\t\t\t\t\t\t<a href=\"https://platum.kr/archives/author/platum\"><span class=\"gravatar\"><img alt=\"Platum\" src=\"https://platum.kr/wp-content/uploads/2013/01/Platum_avatar.jpeg\" class=\"avatar avatar-60 photo\" width=\"60\" height=\"60\"></span><span style=\"float:left; margin:0 12px 0 -2px;\">Platum</span></a>\n\t\t\t\t\t\t\t\t\t\t      \t\t</span>\n\t\t\t      \t\t<span class=\"post_info_date\">\n\t\t\t      \t\t\t<a href=\"https://platum.kr/archives/205957\">Posted On 2023/04/25</a>\n\t\t\t      \t\t</span>\n\t\t\t\t  \t</div>\n\t\t\t   </div>\n\t\t\t   \n\t\t\t   <br class=\"clear\">\n\t    \t\n\t    \t\t\t\t\t\t\n\t\t\t\t    <div class=\"post_img\">\n\t\t\t\t        <a href=\"https://platum.kr/archives/205957\">\n\t\t\t\t        \t\t\t\t\t        \t<img src=\"https://platum.kr/wp-content/uploads/2023/04/AG7I7329-copy-640x427.jpg\" alt=\"\" class=\"\" style=\"width:640px;height:427px;\">\n\t\t\t\t\t    </a>\n\t\t\t\t    </div>\n\t\t\t\t\n\t\t\t\t\t\t\t   \n\t\t\t   \t<br class=\"clear\">\n\t\t\t\t<!-- 원본 소스 BEGIN -->\n\t\t\t\t\t\t\t\t<!-- 원본 소스 END -->\n\n\t\t\t   <!-- Greater China 카테고리 페이지 중국어 글자 수 자르기 BEGIN -->\n\t\t\t   미국 뉴욕에 글로벌비즈니스센터(GBC)가 4월 24일(현지시간) 문을 열었다. 개소식에는 중소벤처기업진흥공단 우영환 부이사장, 미한국상공회의소(KOCHAM) 박호찬 회장, 뉴욕한인경제인협회 유정학 회장을 비롯해 재미한인혁신기술기업인협회, 뉴욕대(NYU), 스티븐스 공과[…]\t\t\t\t<!-- Greater China 카테고리 페이지 중국어 글자 수 자르기 END -->\n\t\t\t   <br class=\"clear\">\n\t\t\t    \n\t\t\t   <div class=\"post_button_wrapper\">\n\t\t\t   <a class=\"readmore\" href=\"https://platum.kr/archives/205957\">Continue Reading</a>\n\t\t\t   </div>\n\t\t\t    \n\t\t\t   <div class=\"post_info_comment\">\n\t\t\t\t<a href=\"https://platum.kr/archives/205957#respond\"><i class=\"fa fa-commenting\"></i>0</a>\n\t\t\t\t</div>\n\t\t\t\t\n\t\t\t\t\t\t\t    \t\t\t\t\n\t\t\t\t<br class=\"clear\"><hr class=\"post_divider\"><hr class=\"post_divider double\">","link":"https://platum.kr/archives/205957","retrieved":1682543567154,"image":"https://platum.kr/wp-content/uploads/2023/04/AG7I7329-copy-640x427.jpg"},{"title":"부산 슬러시드, ‘슬러시드 10’ 참가 스타트업 및 크리에이터 모집","contents":"<div class=\"post_header_title\">\t\n\t\t\t\n\t\t\t\t   \t\t\t\t<!-- 원본 소스 BEGIN -->\n\t\t\t<!--\t\n\t\t\t\t<div class=\"post_info_cat\">\n\t\t\t\t\t<span>\n\t\t\t\t\t\t\t\t\t\t\t<a href=\"https://platum.kr/event\">Event</a>\n\t\t\t\t\t\t\t\t\t\t</span>\n\t\t\t\t</div>\n\t\t\t-->\n\t\t\t<!-- 원본 소스 END -->\n\n\t\t\t<!-- 카테고리 페이지 PC 접근 시 콘텐츠 카테고리 정보 노출 BEGIN -->\n\t\t\t\t\t\t\t\t<div class=\"post_info_cat\">\n\t\t\t\t\t\t<span>\n\t\t\t\t\t    \t\t\t\t\t        <a href=\"https://platum.kr/event\">Event</a>\n\t\t\t\t\t    \t\t\t\t\t\t</span>\n\t\t\t\t\t</div>\n\t\t\t\t\t\t<!-- 카테고리 페이지 PC 접근 시 콘텐츠 카테고리 정보 노출 END -->\n\t\t\t\t\t\t      \t<h5><a href=\"https://platum.kr/archives/205967\" title=\"부산 슬러시드, ‘슬러시드 10’ 참가 스타트업 및 크리에이터 모집\">부산 슬러시드, ‘슬러시드 10’ 참가 스타트업 및 크리에이터 모집</a></h5>\n\t\t\t      \t<div class=\"post_detail post_date\">\n\t\t\t      \t\t<span class=\"post_info_author\">\n\t\t\t\t\t\t\t\t\t\t\t\t\t\t<a href=\"https://platum.kr/archives/author/platum\"><span class=\"gravatar\"><img alt=\"Platum\" src=\"https://platum.kr/wp-content/uploads/2013/01/Platum_avatar.jpeg\" class=\"avatar avatar-60 photo\" width=\"60\" height=\"60\"></span><span style=\"float:left; margin:0 12px 0 -2px;\">Platum</span></a>\n\t\t\t\t\t\t\t\t\t\t      \t\t</span>\n\t\t\t      \t\t<span class=\"post_info_date\">\n\t\t\t      \t\t\t<a href=\"https://platum.kr/archives/205967\">Posted On 2023/04/25</a>\n\t\t\t      \t\t</span>\n\t\t\t\t  \t</div>\n\t\t\t   </div>\n\t\t\t   \n\t\t\t   <br class=\"clear\">\n\t    \t\n\t    \t\t\t\t\t\t\n\t\t\t\t    <div class=\"post_img\">\n\t\t\t\t        <a href=\"https://platum.kr/archives/205967\">\n\t\t\t\t        \t\t\t\t\t        \t<img src=\"https://platum.kr/wp-content/uploads/2023/04/SlushD-640x427.jpg\" alt=\"\" class=\"\" style=\"width:640px;height:427px;\">\n\t\t\t\t\t    </a>\n\t\t\t\t    </div>\n\t\t\t\t\n\t\t\t\t\t\t\t   \n\t\t\t   \t<br class=\"clear\">\n\t\t\t\t<!-- 원본 소스 BEGIN -->\n\t\t\t\t\t\t\t\t<!-- 원본 소스 END -->\n\n\t\t\t   <!-- Greater China 카테고리 페이지 중국어 글자 수 자르기 BEGIN -->\n\t\t\t   코리아스타트업포럼(이하 코스포)이 오는 6월 29일 개최 예정인 ‘부산 슬러시드(BUSAN Slush’D)’에 참가할 스타트업과 크리에이터 ‘슬러시드 10(Slush’D 10, 슬러시드텐)’을 모집한다. 슬러시드 10은 부산 슬러시드가 선발하는 현지 기반의 스타트업과 […]\t\t\t\t<!-- Greater China 카테고리 페이지 중국어 글자 수 자르기 END -->\n\t\t\t   <br class=\"clear\">\n\t\t\t    \n\t\t\t   <div class=\"post_button_wrapper\">\n\t\t\t   <a class=\"readmore\" href=\"https://platum.kr/archives/205967\">Continue Reading</a>\n\t\t\t   </div>\n\t\t\t    \n\t\t\t   <div class=\"post_info_comment\">\n\t\t\t\t<a href=\"https://platum.kr/archives/205967#respond\"><i class=\"fa fa-commenting\"></i>0</a>\n\t\t\t\t</div>\n\t\t\t\t\n\t\t\t\t\t\t\t    \t\t\t\t\n\t\t\t\t<br class=\"clear\"><hr class=\"post_divider\"><hr class=\"post_divider double\">","link":"https://platum.kr/archives/205967","retrieved":1682543567155,"image":"https://platum.kr/wp-content/uploads/2023/04/SlushD-640x427.jpg"}]}